{
  "timestamp": "2026-01-12T20:28:50.891Z",
  "steps": [
    {
      "time": "2026-01-12T20:28:50.894Z",
      "message": "Starting Form Simplicity exploration..."
    },
    {
      "time": "2026-01-12T20:28:51.544Z",
      "message": "Step 1: Navigating to login page..."
    },
    {
      "time": "2026-01-12T20:28:55.730Z",
      "message": "Screenshot saved: 01-login-page.png"
    },
    {
      "time": "2026-01-12T20:28:55.731Z",
      "message": "Login page URL: https://ara.formsimplicity.com/index/signin"
    },
    {
      "time": "2026-01-12T20:28:55.731Z",
      "message": "Step 2: Identifying login form elements..."
    },
    {
      "time": "2026-01-12T20:28:55.832Z",
      "message": "Found username field: input[type=\"text\"]"
    },
    {
      "time": "2026-01-12T20:28:55.864Z",
      "message": "Found password field: input[type=\"password\"]"
    },
    {
      "time": "2026-01-12T20:28:55.882Z",
      "message": "Found submit button: button[type=\"submit\"]"
    },
    {
      "time": "2026-01-12T20:28:55.882Z",
      "message": "Step 3: Attempting login..."
    },
    {
      "time": "2026-01-12T20:28:57.305Z",
      "message": "Screenshot saved: 02-credentials-entered.png"
    },
    {
      "time": "2026-01-12T20:28:57.881Z",
      "message": "Waiting for login to complete..."
    },
    {
      "time": "2026-01-12T20:29:02.802Z",
      "message": "Screenshot saved: 03-after-login.png"
    },
    {
      "time": "2026-01-12T20:29:02.802Z",
      "message": "After login URL: https://ara.formsimplicity.com/users/started"
    },
    {
      "time": "2026-01-12T20:29:02.825Z",
      "message": "WARNING: Login may have failed - check screenshots"
    },
    {
      "time": "2026-01-12T20:29:02.825Z",
      "message": "Step 4: Exploring main page after login..."
    },
    {
      "time": "2026-01-12T20:29:02.931Z",
      "message": "Found 53 navigation links"
    },
    {
      "time": "2026-01-12T20:29:02.989Z",
      "message": "Found create button: button:has-text(\"New\")"
    },
    {
      "time": "2026-01-12T20:29:04.115Z",
      "message": "Found relevant link: \"Blank Forms\" -> javascript:void(0)"
    },
    {
      "time": "2026-01-12T20:29:04.133Z",
      "message": "Found relevant link: \"Forms Library\" -> /formslibrary/formslibrary"
    },
    {
      "time": "2026-01-12T20:29:04.148Z",
      "message": "Found relevant link: \"Forms Packages\" -> /formspackages/"
    },
    {
      "time": "2026-01-12T20:29:04.304Z",
      "message": "Found relevant link: \"Form Simplicity Home page\" -> /users/started"
    },
    {
      "time": "2026-01-12T20:29:04.520Z",
      "message": "Found relevant link: \"Blank Forms\" -> /formslibrary/formslibrary"
    },
    {
      "time": "2026-01-12T20:29:04.534Z",
      "message": "Found relevant link: \"Forms Library\" -> /formslibrary/formslibrary"
    },
    {
      "time": "2026-01-12T20:29:04.550Z",
      "message": "Found relevant link: \"Forms Packages\" -> /formspackages/"
    },
    {
      "time": "2026-01-12T20:29:04.720Z",
      "message": "Found relevant link: \"Create a FormsPackage\" -> #"
    },
    {
      "time": "2026-01-12T20:29:04.752Z",
      "message": "Found relevant link: \"Forms Programming\" -> https://www.formsimplicity.com/order-forms-programming"
    },
    {
      "time": "2026-01-12T20:29:04.834Z",
      "message": "Found relevant link: \"support@formsimplicity.com\" -> mailto:Support@FormSimplicity.com"
    },
    {
      "time": "2026-01-12T20:29:04.857Z",
      "message": "Found relevant link: \"Forms Programming for Form Simplicity\" -> http://www.formsimplicity.com/forms-ordering/"
    },
    {
      "time": "2026-01-12T20:29:04.871Z",
      "message": "Found relevant link: \"Form Simplicity Home page\" -> /users/started"
    },
    {
      "time": "2026-01-12T20:29:04.949Z",
      "message": "Page title: Home | Form Simplicity"
    },
    {
      "time": "2026-01-12T20:29:05.343Z",
      "message": "Screenshot saved: 04-dashboard-overview.png"
    },
    {
      "time": "2026-01-12T20:29:05.343Z",
      "message": "Step 5: Looking for forms/contracts section..."
    },
    {
      "time": "2026-01-12T20:29:05.429Z",
      "message": "Step 6: Searching for Real Estate Contract..."
    },
    {
      "time": "2026-01-12T20:29:05.450Z",
      "message": "Relevant text found on page:"
    },
    {
      "time": "2026-01-12T20:29:05.450Z",
      "message": "  - Blank Forms"
    },
    {
      "time": "2026-01-12T20:29:05.450Z",
      "message": "  - Residential Purchase"
    },
    {
      "time": "2026-01-12T20:29:05.450Z",
      "message": "  - Residential Listing"
    },
    {
      "time": "2026-01-12T20:29:05.450Z",
      "message": "  - Residential Purchase"
    },
    {
      "time": "2026-01-12T20:29:05.450Z",
      "message": "  - Create a Forms"
    },
    {
      "time": "2026-01-12T20:29:05.451Z",
      "message": "  - Forms Programming"
    },
    {
      "time": "2026-01-12T20:29:05.451Z",
      "message": "  - Form Simplicity Home page"
    },
    {
      "time": "2026-01-12T20:29:05.794Z",
      "message": "Screenshot saved: 07-final-state.png"
    }
  ],
  "selectors": {
    "username": "input[type=\"text\"]",
    "password": "input[type=\"password\"]",
    "submit": "button[type=\"submit\"]",
    "createButton": "button:has-text(\"New\")"
  },
  "navigation": {
    "loginUrl": "https://ara.formsimplicity.com/index/signin",
    "dashboardUrl": "https://ara.formsimplicity.com/users/started",
    "pageTitle": "Home | Form Simplicity"
  },
  "loginSuccess": false,
  "relevantText": [
    "Blank Forms",
    "Residential Purchase ",
    "Residential Listing ",
    "Residential Purchase ",
    "Create a Forms",
    "Forms Programming",
    "Form Simplicity Home page"
  ]
}